{
  "default": {
    "flags": [
      {
        "name": "custom_commands",
        "type": "amount",
        "data": {
          "amount": 3
        }
      },
      {
        "name": "prefix_length",
        "type": "amount",
        "data": {
          "amount": 5
        }
      }
    ]
  },
  "cheep": {
    "extras": [
      "tiers.extra.supporter_role",
      "tiers.extra.primary_support"
    ],
    "flags": [
      {
        "name": "custom_commands",
        "type": "amount",
        "data": {
          "amount": 10
        }
      },
      "supporter_badge",
      "more_backgrounds",
      "custom_footer",
      "beta"
    ],
    "parent": "default"
  },
  "medium": {
    "flags": [
      {
        "name": "custom_commands",
        "type": "amount",
        "data": {
          "amount": 20
        }
      },
      {
        "name": "prefix_length",
        "type": "amount",
        "data": {
          "amount": 1900
        }
      },
      "music_services",
      "music_controls",
      "music_soundcloud",
      "custom_backgrounds",
      "planner_agenda",
      "medium_badge"
    ],
    "parent": "cheep"
  },
  "hardcode": {
    "flags": [
      {
        "name": "custom_commands",
        "type": "amount",
        "data": {
          "amount": 50
        }
      },
      "cascade_hosting",
      "hardcode_badge"
    ],
    "extra": [
      "tiers.extra.tshirt"
    ],
    "parent": "medium"
  },
  "example": {
    "__comment": "This is an example tier to show you how the format works",
    "flags": [
      "comment: this stores a list of flags. normal flags are just added to the list with their unique name",
      "example_regular",
      {
        "__comment": "More advanced flags are specified as seen bellow with the name, type, and associated data",
        "name": "example_amount",
        "type": "amount",
        "data": {
          "__comment": "in the case of the amount flag we specify an amount",
          "amount": 5
        }
      }
    ],
    "extras": [
      "Extra strings explaining what you get that the bot it's self doesn't apply. Should be a language file path"
    ],
    "parent": "parent tier that is applied with this tier. flags with same name will be overridden"
  }
}